directory_cms_client/__init__.py
directory_cms_client/client.py
directory_cms_client/constants.py
directory_cms_client/helpers.py
tests/__init__.py
tests/conftest.py
tests/helpers.py
tests/test_client.py
tests/test_constants.py
tests/test_helpers.py
directory_cms_client-12.3.4.dist-info/LICENSE
directory_cms_client-12.3.4.dist-info/METADATA
directory_cms_client-12.3.4.dist-info/WHEEL
directory_cms_client-12.3.4.dist-info/top_level.txt
directory_cms_client-12.3.4.dist-info/RECORD
