Metadata-Version: 2.1
Name: directory-cms-client
Version: 12.3.4
Summary: Python API client for Directory CMS.
Home-page: https://github.com/uktrade/directory-cms-client
Author: Department for International Trade
License: MIT
Platform: UNKNOWN
Classifier: Development Status :: 5 - Production/Stable
Classifier: Environment :: Web Environment
Classifier: Framework :: Django
Classifier: Framework :: Django :: 1.11
Classifier: Framework :: Django :: 3.2
Classifier: Framework :: Django :: 4.2
Classifier: Intended Audience :: Developers
Classifier: License :: OSI Approved :: MIT License
Classifier: Natural Language :: English
Classifier: Operating System :: OS Independent
Classifier: Programming Language :: Python :: 3.6
Classifier: Programming Language :: Python :: 3.9
Classifier: Programming Language :: Python :: Implementation :: PyPy
Classifier: Topic :: Software Development :: Libraries :: Python Modules
Requires-Dist: directory-client-core <8.0.0,>=7.2.8
Provides-Extra: test
Requires-Dist: flake8 ==5.0.4 ; extra == 'test'
Requires-Dist: freezegun ==1.0.0 ; extra == 'test'
Requires-Dist: pytest-django <=4.1.0,>=3.8.0 ; extra == 'test'
Requires-Dist: pytest-sugar <1.0.0,>=0.9.2 ; extra == 'test'
Requires-Dist: pytest ==5.4.0 ; extra == 'test'
Requires-Dist: pytest-codecov ; extra == 'test'
Requires-Dist: pytest-cov ; extra == 'test'
Requires-Dist: GitPython ; extra == 'test'
Requires-Dist: requests-mock ==1.8.0 ; extra == 'test'
Requires-Dist: setuptools <50.0.0,>=45.2.0 ; extra == 'test'
Requires-Dist: twine ; extra == 'test'
Requires-Dist: wheel <1.0.0,>=0.34.2 ; extra == 'test'
